hlochinmay/.python-version
hlochinmay/__init__.py
hlochinmay/hlochinmay.py
hlochinmay-0.1.3.dist-info/entry_points.txt
hlochinmay-0.1.3.dist-info/WHEEL
hlochinmay-0.1.3.dist-info/METADATA
hlochinmay-0.1.3.dist-info/RECORD
