Metadata-Version: 2.1
Name: hlochinmay
Version: 0.1.3
Summary: This package takes name of the user as an argurement in the hello function and then greets the user. from hlochinmay.hlochinmay import hello. hello(<name>)
Author: chinmay
Author-email: bhagyesh.deshmukh29@gmail.com
Requires-Python: >=3.6,<4.0
Classifier: Programming Language :: Python :: 3
Classifier: Programming Language :: Python :: 3.10
Classifier: Programming Language :: Python :: 3.6
Classifier: Programming Language :: Python :: 3.7
Classifier: Programming Language :: Python :: 3.8
Classifier: Programming Language :: Python :: 3.9
